{"trial_id": "4277160f4973ec04ee4eace1975a5a3b", "hyperparameters": {"space": [{"class_name": "Boolean", "config": {"name": "structured_data_block_1/normalize", "default": false, "conditions": []}}, {"class_name": "Boolean", "config": {"name": "structured_data_block_1/dense_block_1/use_batchnorm", "default": false, "conditions": []}}, {"class_name": "Choice", "config": {"name": "structured_data_block_1/dense_block_1/num_layers", "default": 2, "conditions": [], "values": [1, 2, 3], "ordered": true}}, {"class_name": "Choice", "config": {"name": "structured_data_block_1/dense_block_1/units_0", "default": 32, "conditions": [], "values": [16, 32, 64, 128, 256, 512, 1024], "ordered": true}}, {"class_name": "Choice", "config": {"name": "structured_data_block_1/dense_block_1/dropout", "default": 0.0, "conditions": [], "values": [0.0, 0.25, 0.5], "ordered": true}}, {"class_name": "Choice", "config": {"name": "structured_data_block_1/dense_block_1/units_1", "default": 32, "conditions": [], "values": [16, 32, 64, 128, 256, 512, 1024], "ordered": true}}, {"class_name": "Choice", "config": {"name": "classification_head_1/dropout", "default": 0, "conditions": [], "values": [0.0, 0.25, 0.5], "ordered": true}}, {"class_name": "Choice", "config": {"name": "optimizer", "default": "adam", "conditions": [], "values": ["adam", "sgd", "adam_weight_decay"], "ordered": false}}, {"class_name": "Choice", "config": {"name": "learning_rate", "default": 0.001, "conditions": [], "values": [0.1, 0.01, 0.001, 0.0001, 2e-05, 1e-05], "ordered": true}}], "values": {"structured_data_block_1/normalize": true, "structured_data_block_1/dense_block_1/use_batchnorm": true, "structured_data_block_1/dense_block_1/num_layers": 1, "structured_data_block_1/dense_block_1/units_0": 32, "structured_data_block_1/dense_block_1/dropout": 0, "structured_data_block_1/dense_block_1/units_1": 32, "classification_head_1/dropout": 0.0, "optimizer": "adam", "learning_rate": 0.001}}, "metrics": {"metrics": {"loss": {"direction": "min", "observations": [{"value": [0.7014272212982178], "step": 0}, {"value": [0.687093198299408], "step": 1}, {"value": [0.684268593788147], "step": 2}, {"value": [0.6821707487106323], "step": 3}, {"value": [0.679980993270874], "step": 4}, {"value": [0.6777971982955933], "step": 5}, {"value": [0.675620436668396], "step": 6}, {"value": [0.6735014915466309], "step": 7}, {"value": [0.6713998317718506], "step": 8}, {"value": [0.669410765171051], "step": 9}, {"value": [0.6676265001296997], "step": 10}, {"value": [0.6658424735069275], "step": 11}]}, "accuracy": {"direction": "max", "observations": [{"value": [0.5236731171607971], "step": 0}, {"value": [0.5442230701446533], "step": 1}, {"value": [0.5504509210586548], "step": 2}, {"value": [0.5565308928489685], "step": 3}, {"value": [0.5620749592781067], "step": 4}, {"value": [0.5676929354667664], "step": 5}, {"value": [0.5736805200576782], "step": 6}, {"value": [0.5780972838401794], "step": 7}, {"value": [0.5821813941001892], "step": 8}, {"value": [0.5859143733978271], "step": 9}, {"value": [0.5892778038978577], "step": 10}, {"value": [0.5915693640708923], "step": 11}]}, "val_loss": {"direction": "min", "observations": [{"value": [0.6947128176689148], "step": 0}, {"value": [0.6939164400100708], "step": 1}, {"value": [0.6941727995872498], "step": 2}, {"value": [0.6944924592971802], "step": 3}, {"value": [0.6952197551727295], "step": 4}, {"value": [0.6962826251983643], "step": 5}, {"value": [0.6976718306541443], "step": 6}, {"value": [0.699044406414032], "step": 7}, {"value": [0.7005794644355774], "step": 8}, {"value": [0.7020437717437744], "step": 9}, {"value": [0.7034505009651184], "step": 10}, {"value": [0.7049124836921692], "step": 11}]}, "val_accuracy": {"direction": "max", "observations": [{"value": [0.5201125741004944], "step": 0}, {"value": [0.524483323097229], "step": 1}, {"value": [0.527446448802948], "step": 2}, {"value": [0.5267056822776794], "step": 3}, {"value": [0.5277428030967712], "step": 4}, {"value": [0.5251500010490417], "step": 5}, {"value": [0.5251500010490417], "step": 6}, {"value": [0.5242610573768616], "step": 7}, {"value": [0.5223349928855896], "step": 8}, {"value": [0.5195199847221375], "step": 9}, {"value": [0.5195940732955933], "step": 10}, {"value": [0.5200385451316833], "step": 11}]}}}, "score": 0.5277428030967712, "best_step": 4, "status": "COMPLETED"}